compare_dfs/__init__.py
compare_dfs-0.0.6.dist-info/LICENSE
compare_dfs-0.0.6.dist-info/METADATA
compare_dfs-0.0.6.dist-info/WHEEL
compare_dfs-0.0.6.dist-info/top_level.txt
compare_dfs-0.0.6.dist-info/RECORD
